SimplestAI/__init__.py
SimplestAI-0.0a1.dist-info/LICENSE
SimplestAI-0.0a1.dist-info/METADATA
SimplestAI-0.0a1.dist-info/WHEEL
SimplestAI-0.0a1.dist-info/top_level.txt
SimplestAI-0.0a1.dist-info/RECORD
