Metadata-Version: 2.1
Name: SimplestAI
Version: 0.0a1
Summary: The simplest AI package. Q-method included!
Home-page: https://github.com/alexbronikitin/SimplestAI
Author: Hamstory Game Studio (Cubic)
Author-email: hamstory.game.studio@gmail.com
License: UNKNOWN
Project-URL: Bug Tracker, https://github.com/alexbronikitin/SimplestAI/issues
Project-URL: Our Minecraft Server!, https://2v2c.tilda.ws
Platform: UNKNOWN
Classifier: Programming Language :: Python :: 3
Classifier: License :: OSI Approved :: MIT License
Classifier: Operating System :: OS Independent
Requires-Python: >=3.6
License-File: LICENSE
